{"System": {"system_id": 1199, "site_id": 1196, "public_name": "[1199] Distributed Sun - Hunt Valley", "area": "366.544", "power": "52.92", "started_on": "2010-05-26 15:45:00", "ended_on": "", "comments": "PVDAQ contributor Washington D.C. area"}, "Site": {"site_id": "1196", "public_name": "[1199] Distributed Sun - Hunt Valley", "latitude": "39.4856", "longitude": "-76.6636", "elevation": "325.0", "climate_type": "Cfa", "av_temp": "16.0", "av_pressure": "1020.0"}, "Mount": {"Mount 0": {"mount_id": 1194, "name": "ds-hv_1199_mt1", "manufacturer": "", "model": "", "tracking": "f", "azimuth": "180.0", "tilt": "20.0"}}, "Inverters": {"Inverter 0": {"inverter_id": "1180", "name": "disu-huva_1199_inv_0", "manufacturer": "SMA", "model": "SB7000W", "type": "string", "quantity": "7", "serial_num": "", "comments": "", "time_interval": "", "modules_per_string": "", "num_strings": ""}}, "Modules": {"Module 0": {"module_id": "1194", "inverter_id": "1180", "name": "disu-huva_1199_m1", "manufacturer": "Suntech", "model": "280W", "type": "multi-Si", "quantity": "189", "start_on": "2010-05-26 09:45:00", "end_on": "", "serial_num": "", "reference_module": "False", "comments": ""}}, "Meters": {}, "Other Instruments": {}}